unimore_math1/__init__.py
unimore_math1/my_math.py
unimore_math1-0.2.dist-info/METADATA
unimore_math1-0.2.dist-info/WHEEL
unimore_math1-0.2.dist-info/top_level.txt
unimore_math1-0.2.dist-info/RECORD
